context_protector/__init__.py
context_protector/__main__.py
context_protector/config.py
context_protector/guardrail_types.py
context_protector/guardrails.py
context_protector/hook_handler.py
context_protector/providers/__init__.py
context_protector/providers/apriel_guard.py
context_protector/providers/base.py
context_protector/providers/gcpmodelarmor_provider.py
context_protector/providers/llama_firewall.py
context_protector/providers/mock_provider.py
context_protector/providers/nemo_guardrails.py
context_protector-1.0.0.dist-info/WHEEL
context_protector-1.0.0.dist-info/entry_points.txt
context_protector-1.0.0.dist-info/METADATA
context_protector-1.0.0.dist-info/RECORD
