Metadata-Version: 2.3
Name: context-protector
Version: 1.0.0
Summary: Vendor-neutral guardrails for AI coding agents. Protects against prompt injection attacks.
Keywords: prompt-injection,guardrails,llm-security,ai-safety,claude-code,opencode,ai-coding-agent
Author: Otto Sulin
Author-email: Otto Sulin <otto.sulin@protonmail.com>
License: MIT
Classifier: Development Status :: 4 - Beta
Classifier: Environment :: Console
Classifier: Intended Audience :: Developers
Classifier: License :: OSI Approved :: MIT License
Classifier: Operating System :: OS Independent
Classifier: Programming Language :: Python :: 3
Classifier: Programming Language :: Python :: 3.12
Classifier: Programming Language :: Python :: 3.13
Classifier: Topic :: Security
Classifier: Topic :: Software Development :: Quality Assurance
Classifier: Typing :: Typed
Requires-Dist: llamafirewall>=1.0.3
Requires-Dist: pyyaml>=6.0
Requires-Dist: nemoguardrails[all]>=0.19.0
Requires-Dist: langchain-ollama>=1.0.1
Requires-Dist: google-cloud-modelarmor>=0.4.0
Requires-Dist: context-protector[aprielguard] ; extra == 'all'
Requires-Dist: transformers>=4.40.0 ; extra == 'aprielguard'
Requires-Dist: torch>=2.0.0 ; extra == 'aprielguard'
Requires-Python: >=3.12
Project-URL: Documentation, https://github.com/ottosulin/context-protector#readme
Project-URL: Homepage, https://github.com/ottosulin/context-protector
Project-URL: Issues, https://github.com/ottosulin/context-protector/issues
Project-URL: Repository, https://github.com/ottosulin/context-protector
Provides-Extra: all
Provides-Extra: aprielguard
